jumpad_sdk_client/__init__.py
jumpad_sdk_client/client.py
jumpad_sdk_client-0.1.1.dist-info/licenses/LICENSE
jumpad_sdk_client-0.1.1.dist-info/METADATA
jumpad_sdk_client-0.1.1.dist-info/WHEEL
jumpad_sdk_client-0.1.1.dist-info/top_level.txt
jumpad_sdk_client-0.1.1.dist-info/RECORD
