Metadata-Version: 2.4
Name: jumpad-sdk-client
Version: 0.1.1
Summary: A powerful and user-friendly Python client for interacting with the Jumpad AI Agent SDK
Home-page: https://github.com/jumpad-ai/jumpad-python-sdk
Author: Jumpad AI
Author-email: info@jumpad.ai
Classifier: Programming Language :: Python :: 3
Classifier: License :: OSI Approved :: MIT License
Classifier: Operating System :: OS Independent
Requires-Python: >=3.6
License-File: LICENSE
Requires-Dist: requests>=2.25.0
Dynamic: author
Dynamic: author-email
Dynamic: classifier
Dynamic: description
Dynamic: description-content-type
Dynamic: home-page
Dynamic: license-file
Dynamic: requires-dist
Dynamic: requires-python
Dynamic: summary
